slice/__init__.py
slice/slice.py
slice_qtc-0.1.2.dist-info/LICENSE
slice_qtc-0.1.2.dist-info/METADATA
slice_qtc-0.1.2.dist-info/WHEEL
slice_qtc-0.1.2.dist-info/entry_points.txt
slice_qtc-0.1.2.dist-info/RECORD
